wheel_stub/ERROR.txt
wheel_stub/__about__.py
wheel_stub/__init__.py
wheel_stub/buildapi.py
wheel_stub/common.py
wheel_stub/error.py
wheel_stub/sdist.py
wheel_stub/wheel.py
wheel_stub/_vendor/README.md
wheel_stub/_vendor/__init__.py
wheel_stub/_vendor/packaging/__init__.py
wheel_stub/_vendor/packaging/_elffile.py
wheel_stub/_vendor/packaging/_manylinux.py
wheel_stub/_vendor/packaging/_musllinux.py
wheel_stub/_vendor/packaging/_parser.py
wheel_stub/_vendor/packaging/_structures.py
wheel_stub/_vendor/packaging/_tokenizer.py
wheel_stub/_vendor/packaging/markers.py
wheel_stub/_vendor/packaging/metadata.py
wheel_stub/_vendor/packaging/py.typed
wheel_stub/_vendor/packaging/requirements.py
wheel_stub/_vendor/packaging/specifiers.py
wheel_stub/_vendor/packaging/tags.py
wheel_stub/_vendor/packaging/utils.py
wheel_stub/_vendor/packaging/version.py
wheel_stub/_vendor/packaging-24.1.dist-info/INSTALLER
wheel_stub/_vendor/packaging-24.1.dist-info/LICENSE
wheel_stub/_vendor/packaging-24.1.dist-info/LICENSE.APACHE
wheel_stub/_vendor/packaging-24.1.dist-info/LICENSE.BSD
wheel_stub/_vendor/packaging-24.1.dist-info/METADATA
wheel_stub/_vendor/packaging-24.1.dist-info/RECORD
wheel_stub/_vendor/packaging-24.1.dist-info/REQUESTED
wheel_stub/_vendor/packaging-24.1.dist-info/WHEEL
wheel_stub/_vendor/tomli/__init__.py
wheel_stub/_vendor/tomli/_parser.py
wheel_stub/_vendor/tomli/_re.py
wheel_stub/_vendor/tomli/_types.py
wheel_stub/_vendor/tomli/py.typed
wheel_stub/_vendor/tomli-2.0.1.dist-info/INSTALLER
wheel_stub/_vendor/tomli-2.0.1.dist-info/LICENSE
wheel_stub/_vendor/tomli-2.0.1.dist-info/METADATA
wheel_stub/_vendor/tomli-2.0.1.dist-info/RECORD
wheel_stub/_vendor/tomli-2.0.1.dist-info/REQUESTED
wheel_stub/_vendor/tomli-2.0.1.dist-info/WHEEL
wheel_stub-0.4.2.dist-info/METADATA
wheel_stub-0.4.2.dist-info/WHEEL
wheel_stub-0.4.2.dist-info/licenses/LICENSE
wheel_stub-0.4.2.dist-info/RECORD
